hifigan_ts_vocoder/__init__.py
hifigan_ts_vocoder/vocoder.py
hifigan_ts_vocoder-0.1.1.data/data/ckpts/hfgan-fcm_base2-L-16k-v0.1.1.ts
hifigan_ts_vocoder-0.1.1.dist-info/METADATA
hifigan_ts_vocoder-0.1.1.dist-info/WHEEL
hifigan_ts_vocoder-0.1.1.dist-info/top_level.txt
hifigan_ts_vocoder-0.1.1.dist-info/RECORD
