Metadata-Version: 2.1
Name: hifigan-ts-vocoder
Version: 0.1.1
Summary: A demo for python packaging.
Home-page: https://github.com/RongSong1993/zhiyundemo
Author: LG_SS
Author-email: liug25@mail2.sysu.edu.cn
License: MIT
Keywords: demo
Platform: UNKNOWN
